immunopipe/__init__.py
immunopipe/__main__.py
immunopipe/cli_help.py
immunopipe/cli_utils/AGENTS.md
immunopipe/cli_utils/__init__.py
immunopipe/cli_utils/check_dim.R
immunopipe/cli_utils/check_dim.py
immunopipe/cli_utils/check_genes.R
immunopipe/cli_utils/check_genes.py
immunopipe/cli_utils/utils.py
immunopipe/gbatch.py
immunopipe/inhouse.py
immunopipe/mcp/AGENTS.md
immunopipe/mcp/README.md
immunopipe/mcp/__init__.py
immunopipe/mcp/doc_extractor.py
immunopipe/mcp/example.py
immunopipe/mcp/mcp_server.py
immunopipe/mcp/options.py
immunopipe/mcp/server.py
immunopipe/mcp/toml_generator.py
immunopipe/mcp/tools.py
immunopipe/pipeline.py
immunopipe/processes.py
immunopipe/reports/CloneHeterogeneity.svelte
immunopipe/reports/MarkersOverlapping.svelte
immunopipe/reports/TCellSelection.svelte
immunopipe/reports/TOrBCellSelection.svelte
immunopipe/router.py
immunopipe/scripts/CloneHeterogeneity.R
immunopipe/scripts/LoadingRNAFromSeurat.R
immunopipe/scripts/MarkersOverlapping.R
immunopipe/scripts/TCellSelection.R
immunopipe/scripts/TOrBCellSelection.R
immunopipe/validate_config.py
immunopipe/version.py
immunopipe-2.3.2.dist-info/METADATA
immunopipe-2.3.2.dist-info/WHEEL
immunopipe-2.3.2.dist-info/entry_points.txt
immunopipe-2.3.2.dist-info/licenses/LICENSE
immunopipe-2.3.2.dist-info/RECORD
