Metadata-Version: 2.4
Name: immunopipe
Version: 2.3.2
Summary: A pipeline for integrative analysis for scRNA-seq and scTCR-/scBCR-seq data
License: GNU General Public License v3.0
License-File: LICENSE
Author: pwwang
Author-email: pwwang@pwwang.com
Requires-Python: >=3.9,<4.0
Classifier: License :: Other/Proprietary License
Classifier: Programming Language :: Python :: 3
Classifier: Programming Language :: Python :: 3.9
Classifier: Programming Language :: Python :: 3.10
Classifier: Programming Language :: Python :: 3.11
Classifier: Programming Language :: Python :: 3.12
Classifier: Programming Language :: Python :: 3.13
Classifier: Programming Language :: Python :: 3.14
Provides-Extra: cli-gbatch
Provides-Extra: diagram
Provides-Extra: dry
Provides-Extra: runinfo
Requires-Dist: biopipen (>=1.1.7,<2.0.0)
Requires-Dist: pipen-cli-gbatch (>=1.1,<2.0) ; extra == "cli-gbatch"
Requires-Dist: pipen-diagram (>=1.1,<2.0) ; extra == "diagram"
Requires-Dist: pipen-dry (>=1.1,<2.0) ; extra == "dry"
Requires-Dist: pipen-runinfo (>=1.1,<2.0) ; extra == "runinfo"
Project-URL: Homepage, https://github.com/pwwang/immunopipe
Project-URL: Repository, https://github.com/pwwang/immunopipe
